{
	"class" : {
		 },
	"instance" : {
		"actionCloseFile" : "lra 6/12/2022 18:47",
		"actionOpenFile" : "lra 6/12/2022 19:17",
		"actionSaveFile" : "lra 6/12/2022 19:17",
		"askOpenPath" : "lha 5/17/2022 19:27",
		"askSavePath" : "lha 5/17/2022 19:28",
		"canCloseFile" : "lra 8/5/2022 16:18",
		"canSaveFile" : "lha 5/17/2022 19:28",
		"displayNameOf:" : "aes 5/27/2022 14:20",
		"getChildrenOf:" : "aes 5/27/2022 13:58",
		"getReadStreamForFileNamed:" : "lha 5/17/2022 19:28",
		"getWriteStreamForFileNamed:" : "lha 5/17/2022 19:28",
		"hasChildren:" : "aes 5/27/2022 14:23",
		"infoForSelectedElement" : "aes 5/28/2022 13:05",
		"selectElement:" : "lra 6/12/2022 15:40",
		"selectedElement" : "aes 5/27/2022 14:19",
		"selectedElement:" : "lra 6/12/2022 16:58",
		"selectedPath" : "aes 5/28/2022 14:36",
		"selectedPath:" : "lra 6/12/2022 15:40",
		"svg" : "lra 6/12/2022 16:14",
		"svg:" : "aes 5/27/2022 14:11",
		"svgTree" : "aes 5/27/2022 14:22",
		"windowTitle" : "lha 5/17/2022 20:29" } }
